toc/__init__.py
toc/check_cfg_ambiguity.py
toc/nfa_to_dfa.py
toc/tm_add_two_unary_nums.py
computation_toolkit-1.dist-info/METADATA
computation_toolkit-1.dist-info/WHEEL
computation_toolkit-1.dist-info/top_level.txt
computation_toolkit-1.dist-info/RECORD
