Metadata-Version: 2.4
Name: computation_toolkit
Version: 1
Summary: Theory of Computation
Home-page: https://github.com/Ammar-Khaled/automata_practical_exam_ammar_khaled.git
Author: Ammar Khaled
Author-email: 
Classifier: Programming Language :: Python :: 3
Classifier: License :: OSI Approved :: MIT License
Classifier: Operating System :: OS Independent
Requires-Python: >=3.6
Dynamic: author
Dynamic: classifier
Dynamic: description
Dynamic: description-content-type
Dynamic: home-page
Dynamic: requires-python
Dynamic: summary
